README.md
frasco_tasks.py
setup.py
frasco_tasks.egg-info/PKG-INFO
frasco_tasks.egg-info/SOURCES.txt
frasco_tasks.egg-info/dependency_links.txt
frasco_tasks.egg-info/not-zip-safe
frasco_tasks.egg-info/requires.txt
frasco_tasks.egg-info/top_level.txt