Metadata-Version: 1.0
Name: frasco-tasks
Version: 0.4.5
Summary: Celery integration for Frasco
Home-page: http://github.com/frascoweb/frasco-tasks
Author: Maxime Bouroumeau-Fuseau
Author-email: maxime.bouroumeau@gmail.com
License: MIT
Platform: any
